cda_dl/__init__.py
cda_dl/download_options.py
cda_dl/download_state.py
cda_dl/downloader.py
cda_dl/error.py
cda_dl/folder.py
cda_dl/main.py
cda_dl/ui.py
cda_dl/utils.py
cda_dl/version.py
cda_dl/video.py
cda_dl-1.1.9.dist-info/LICENSE
cda_dl-1.1.9.dist-info/METADATA
cda_dl-1.1.9.dist-info/WHEEL
cda_dl-1.1.9.dist-info/entry_points.txt
cda_dl-1.1.9.dist-info/top_level.txt
cda_dl-1.1.9.dist-info/RECORD
