Metadata-Version: 2.1
Name: cda-dl
Version: 1.1.9
Summary: CLI downloader do filmów i folderów z cda.pl
Author: Piotr Skowroński
License: MIT
Classifier: Topic :: Multimedia :: Video
Classifier: Environment :: Console
Classifier: Programming Language :: Python :: 3
Classifier: License :: OSI Approved :: MIT License
Requires-Python: >=3.10
License-File: LICENSE
Requires-Dist: aiofiles
Requires-Dist: aiohttp
Requires-Dist: asyncio
Requires-Dist: bs4
Requires-Dist: rich
Requires-Dist: tenacity
Provides-Extra: formatting
Requires-Dist: black ; extra == 'formatting'
Provides-Extra: linting
Requires-Dist: flake8 ; extra == 'linting'
Requires-Dist: mypy ; extra == 'linting'
Provides-Extra: testing
Requires-Dist: pytest ; extra == 'testing'
Requires-Dist: pytest-asyncio ; extra == 'testing'
Requires-Dist: tox ; extra == 'testing'
